<cookies>
	<cookie id="NID">
		<host>.google.com</host>
		<isdomain>TRUE</isdomain>
		<path>/</path>
		<issecure>FALSE</issecure>
		<expires>1494074130</expires>
		<name>NID</name>
		<value><![CDATA[90=DCU0NOm4hVIX_YCJFBSfGoOrJ9dUGweU96SojXPWo8vVOszBlHkr9sfasLOVTmINHuPrZbq98o52cgg1fkcJ3gjop77Q77IRetH4_Rs0M7OWw6ckCqE3dHSSiDs3iznr]]></value>
		<policy>0</policy>
		<status>0</status>
	</cookie>
	<cookie id="ruid">
		<host>.rubiconproject.com</host>
		<isdomain>TRUE</isdomain>
		<path>/</path>
		<issecure>FALSE</issecure>
		<expires>1486038935</expires>
		<name>ruid</name>
		<value><![CDATA[591ffca4581c80955ff5cb8d2135cc^1^1478262933^1609943949]]></value>
		<policy>0</policy>
		<status>0</status>
	</cookie>
	<cookie id="rsid">
		<host>.rubiconproject.com</host>
		<isdomain>TRUE</isdomain>
		<path>/</path>
		<issecure>FALSE</issecure>
		<expires>0</expires>
		<name>rsid</name>
		<value><![CDATA[EsuOVS/zp8dPD+Hie0dN0+91IqbT+15VpvvoE16N7S94Q4OhPXT5SJUHHOA/m8Qxsrkguh57oB3KcuItf4JuFpBe9pw6JSWDZt2m5c29XOtKD91e7km1D28Ek3czxA+tUvTjPcsACa1R6U2I4m29pLW/Aw==]]></value>
		<policy>0</policy>
		<status>0</status>
	</cookie>
	<cookie id="rdk57">
		<host>.rubiconproject.com</host>
		<isdomain>TRUE</isdomain>
		<path>/</path>
		<issecure>FALSE</issecure>
		<expires>1478262945</expires>
		<name>rdk57</name>
		<value><![CDATA[0]]></value>
		<policy>0</policy>
		<status>0</status>
	</cookie>
	<cookie id="ses57">
		<host>.rubiconproject.com</host>
		<isdomain>TRUE</isdomain>
		<path>/</path>
		<issecure>FALSE</issecure>
		<expires>1478329201</expires>
		<name>ses57</name>
		<value><![CDATA[45718^1]]></value>
		<policy>0</policy>
		<status>0</status>
	</cookie>
	<cookie id="vis57">
		<host>.rubiconproject.com</host>
		<isdomain>TRUE</isdomain>
		<path>/</path>
		<issecure>FALSE</issecure>
		<expires>1478329201</expires>
		<name>vis57</name>
		<value><![CDATA[45718^1]]></value>
		<policy>0</policy>
		<status>0</status>
	</cookie>
	<cookie id="csi57">
		<host>.rubiconproject.com</host>
		<isdomain>TRUE</isdomain>
		<path>/</path>
		<issecure>FALSE</issecure>
		<expires>1478867735</expires>
		<name>csi57</name>
		<value><![CDATA[]]></value>
		<policy>0</policy>
		<status>0</status>
	</cookie>
	<cookie id="csc57">
		<host>.rubiconproject.com</host>
		<isdomain>TRUE</isdomain>
		<path>/</path>
		<issecure>FALSE</issecure>
		<expires>1478867735</expires>
		<name>csc57</name>
		<value><![CDATA[]]></value>
		<policy>0</policy>
		<status>0</status>
	</cookie>
	<cookie id="rdk">
		<host>.rubiconproject.com</host>
		<isdomain>TRUE</isdomain>
		<path>/</path>
		<issecure>FALSE</issecure>
		<expires>1478262997</expires>
		<name>rdk</name>
		<value><![CDATA[10653/45614]]></value>
		<policy>0</policy>
		<status>0</status>
	</cookie>
	<cookie id="rdk2">
		<host>.rubiconproject.com</host>
		<isdomain>TRUE</isdomain>
		<path>/</path>
		<issecure>FALSE</issecure>
		<expires>1478262947</expires>
		<name>rdk2</name>
		<value><![CDATA[0]]></value>
		<policy>0</policy>
		<status>0</status>
	</cookie>
	<cookie id="ses2">
		<host>.rubiconproject.com</host>
		<isdomain>TRUE</isdomain>
		<path>/</path>
		<issecure>FALSE</issecure>
		<expires>1478329202</expires>
		<name>ses2</name>
		<value><![CDATA[45614^1&45718^1]]></value>
		<policy>0</policy>
		<status>0</status>
	</cookie>
	<cookie id="vis2">
		<host>.rubiconproject.com</host>
		<isdomain>TRUE</isdomain>
		<path>/</path>
		<issecure>FALSE</issecure>
		<expires>1478329202</expires>
		<name>vis2</name>
		<value><![CDATA[45614^1&45718^1]]></value>
		<policy>0</policy>
		<status>0</status>
	</cookie>
	<cookie id="csi2">
		<host>.rubiconproject.com</host>
		<isdomain>TRUE</isdomain>
		<path>/</path>
		<issecure>FALSE</issecure>
		<expires>1478867737</expires>
		<name>csi2</name>
		<value><![CDATA[]]></value>
		<policy>0</policy>
		<status>0</status>
	</cookie>
	<cookie id="csc2">
		<host>.rubiconproject.com</host>
		<isdomain>TRUE</isdomain>
		<path>/</path>
		<issecure>FALSE</issecure>
		<expires>1478867737</expires>
		<name>csc2</name>
		<value><![CDATA[]]></value>
		<policy>0</policy>
		<status>0</status>
	</cookie>
	<cookie id="uid">
		<host>.redintelligence.net</host>
		<isdomain>TRUE</isdomain>
		<path>/</path>
		<issecure>FALSE</issecure>
		<expires>1486038942</expires>
		<name>uid</name>
		<value><![CDATA[9f8fd3009dbd8e79]]></value>
		<policy>0</policy>
		<status>0</status>
	</cookie>
	<cookie id="pid">
		<host>.smartadserver.com</host>
		<isdomain>TRUE</isdomain>
		<path>/</path>
		<issecure>FALSE</issecure>
		<expires>1509366941</expires>
		<name>pid</name>
		<value><![CDATA[-1804675841128333254]]></value>
		<policy>0</policy>
		<status>0</status>
	</cookie>
	<cookie id="TestIfCookieP">
		<host>.smartadserver.com</host>
		<isdomain>TRUE</isdomain>
		<path>/</path>
		<issecure>FALSE</issecure>
		<expires>1509366941</expires>
		<name>TestIfCookieP</name>
		<value><![CDATA[ok]]></value>
		<policy>0</policy>
		<status>0</status>
	</cookie>
	<cookie id="csync">
		<host>.smartadserver.com</host>
		<isdomain>TRUE</isdomain>
		<path>/</path>
		<issecure>FALSE</issecure>
		<expires>1509366941</expires>
		<name>csync</name>
		<value><![CDATA[76:CAESED_M2qWPcvwIogGoKHU7Ils]]></value>
		<policy>0</policy>
		<status>0</status>
	</cookie>
	<cookie id="id">
		<host>.mookie1.com</host>
		<isdomain>TRUE</isdomain>
		<path>/</path>
		<issecure>FALSE</issecure>
		<expires>1512390942</expires>
		<name>id</name>
		<value><![CDATA[11407054906239769397]]></value>
		<policy>0</policy>
		<status>0</status>
	</cookie>
	<cookie id="mdata">
		<host>.mookie1.com</host>
		<isdomain>TRUE</isdomain>
		<path>/</path>
		<issecure>FALSE</issecure>
		<expires>1512390942</expires>
		<name>mdata</name>
		<value><![CDATA[1|11407054906239769397|1478262939823]]></value>
		<policy>0</policy>
		<status>0</status>
	</cookie>
	<cookie id="syncdata_DBC">
		<host>.mookie1.com</host>
		<isdomain>TRUE</isdomain>
		<path>/</path>
		<issecure>FALSE</issecure>
		<expires>1479126942</expires>
		<name>syncdata_DBC</name>
		<value><![CDATA[11407054906239769397|CAESEFYtgmS7ROhyKOBKyQDNVSY|1478262939]]></value>
		<policy>0</policy>
		<status>0</status>
	</cookie>
	<cookie id="wtsid_752252631714867">
		<host>editorialelibero01.webtrekk.net</host>
		<isdomain>FALSE</isdomain>
		<path>/752252631714867/</path>
		<issecure>FALSE</issecure>
		<expires>0</expires>
		<name>wtsid_752252631714867</name>
		<value><![CDATA[1]]></value>
		<policy>0</policy>
		<status>0</status>
	</cookie>
	<cookie id="wteid_752252631714867">
		<host>editorialelibero01.webtrekk.net</host>
		<isdomain>FALSE</isdomain>
		<path>/752252631714867/</path>
		<issecure>FALSE</issecure>
		<expires>1493814939</expires>
		<name>wteid_752252631714867</name>
		<value><![CDATA[4147826292900505497]]></value>
		<policy>0</policy>
		<status>0</status>
	</cookie>
	<cookie id="IMRID">
		<host>.imrworldwide.com</host>
		<isdomain>TRUE</isdomain>
		<path>/</path>
		<issecure>FALSE</issecure>
		<expires>1541334932</expires>
		<name>IMRID</name>
		<value><![CDATA[815eb29d-99dd-4a1a-991e-90d190960d43]]></value>
		<policy>0</policy>
		<status>0</status>
	</cookie>
	<cookie id="zptpvc">
		<host>.zanox.com</host>
		<isdomain>TRUE</isdomain>
		<path>/</path>
		<issecure>FALSE</issecure>
		<expires>1486038944</expires>
		<name>zptpvc</name>
		<value><![CDATA[5C55842S2229600324271193094T0II5C266318S2229600324275387392T0II20292776C0SV1yq659909824851332257y99y9bT2229600324271193094]]></value>
		<policy>0</policy>
		<status>0</status>
	</cookie>
	<cookie id="zpvc">
		<host>ad.zanox.com</host>
		<isdomain>FALSE</isdomain>
		<path>/</path>
		<issecure>FALSE</issecure>
		<expires>1480854944</expires>
		<name>zpvc</name>
		<value><![CDATA[5C17762S2229600325667850246T0II5C138493S2229600325722376192T0II28206019C0SV1yq659909824851332257y99y9bT2229600325667850246]]></value>
		<policy>0</policy>
		<status>0</status>
	</cookie>
	<cookie id="ASP.NET_SessionId">
		<host>videosynd.kataweb.it</host>
		<isdomain>FALSE</isdomain>
		<path>/</path>
		<issecure>FALSE</issecure>
		<expires>0</expires>
		<name>ASP.NET_SessionId</name>
		<value><![CDATA[ctyh2igwiyrep21mmu1surtx]]></value>
		<policy>0</policy>
		<status>0</status>
	</cookie>
	<cookie id="adaptv_page_url">
		<host>.adaptv.advertising.com</host>
		<isdomain>TRUE</isdomain>
		<path>/</path>
		<issecure>FALSE</issecure>
		<expires>1478262994</expires>
		<name>adaptv_page_url</name>
		<value><![CDATA["M3h9qeyoFhilJJ6HSKW-ItJLc1UI8SssPztPDyZiQD98fBfNhIcgq6ObnuJPGA7mA4TPsDL0XpXPdDExwrOhlsihALCw8x-/j61mD58ztDckvlAcrdWTSkXJlBbZsO5V"]]></value>
		<policy>0</policy>
		<status>0</status>
	</cookie>
	<cookie id="sourceck">
		<host>.infostrada.it</host>
		<isdomain>TRUE</isdomain>
		<path>/</path>
		<issecure>FALSE</issecure>
		<expires>1478608544</expires>
		<name>sourceck</name>
		<value><![CDATA[701000-1478262896]]></value>
		<policy>0</policy>
		<status>0</status>
	</cookie>
	<cookie id="uvc">
		<host>.addthis.com</host>
		<isdomain>TRUE</isdomain>
		<path>/</path>
		<issecure>FALSE</issecure>
		<expires>1541334939</expires>
		<name>uvc</name>
		<value><![CDATA[1%7C44]]></value>
		<policy>0</policy>
		<status>0</status>
	</cookie>
	<cookie id="bt2">
		<host>.addthis.com</host>
		<isdomain>TRUE</isdomain>
		<path>/</path>
		<issecure>FALSE</issecure>
		<expires>1500381340</expires>
		<name>bt2</name>
		<value><![CDATA[581c809a001Fs0002001Ps0002004Js0002]]></value>
		<policy>0</policy>
		<status>0</status>
	</cookie>
	<cookie id="di2">
		<host>.addthis.com</host>
		<isdomain>TRUE</isdomain>
		<path>/</path>
		<issecure>FALSE</issecure>
		<expires>1541334940</expires>
		<name>di2</name>
		<value><![CDATA[aUhuU#$>f6Hq]]></value>
		<policy>0</policy>
		<status>0</status>
	</cookie>
	<cookie id="uid">
		<host>.addthis.com</host>
		<isdomain>TRUE</isdomain>
		<path>/</path>
		<issecure>FALSE</issecure>
		<expires>1541334940</expires>
		<name>uid</name>
		<value><![CDATA[581c809af692cccd]]></value>
		<policy>0</policy>
		<status>0</status>
	</cookie>
	<cookie id="vc">
		<host>.addthis.com</host>
		<isdomain>TRUE</isdomain>
		<path>/</path>
		<issecure>FALSE</issecure>
		<expires>1541334940</expires>
		<name>vc</name>
		<value><![CDATA[2]]></value>
		<policy>0</policy>
		<status>0</status>
	</cookie>
	<cookie id="loc">
		<host>.addthis.com</host>
		<isdomain>TRUE</isdomain>
		<path>/</path>
		<issecure>FALSE</issecure>
		<expires>1541334940</expires>
		<name>loc</name>
		<value><![CDATA[MDAwMDBFVUlUMDAyMjU1MTg5MjAwMDAwMDAwVg==]]></value>
		<policy>0</policy>
		<status>0</status>
	</cookie>
	<cookie id="sessionId">
		<host>ads.stickyadstv.com</host>
		<isdomain>FALSE</isdomain>
		<path>/</path>
		<issecure>FALSE</issecure>
		<expires>0</expires>
		<name>sessionId</name>
		<value><![CDATA[e2774e533d7fee1f79978d09bbefa15]]></value>
		<policy>0</policy>
		<status>0</status>
	</cookie>
	<cookie id="UID">
		<host>ads.stickyadstv.com</host>
		<isdomain>FALSE</isdomain>
		<path>/</path>
		<issecure>FALSE</issecure>
		<expires>1480854941</expires>
		<name>UID</name>
		<value><![CDATA[5bd1eebad0cdebce4d7ce192a2b5b84]]></value>
		<policy>0</policy>
		<status>0</status>
	</cookie>
	<cookie id="uid-bp-159">
		<host>ads.stickyadstv.com</host>
		<isdomain>FALSE</isdomain>
		<path>/</path>
		<issecure>FALSE</issecure>
		<expires>1509798941</expires>
		<name>uid-bp-159</name>
		<value><![CDATA[CAESEG3GLbiLMHMVQd1Gq4UMzx0]]></value>
		<policy>0</policy>
		<status>0</status>
	</cookie>
	<cookie id="__utmc">
		<host>.corrieredellumbria.corr.it</host>
		<isdomain>TRUE</isdomain>
		<path>/</path>
		<issecure>FALSE</issecure>
		<expires>0</expires>
		<name>__utmc</name>
		<value><![CDATA[128286110]]></value>
		<policy>0</policy>
		<status>0</status>
	</cookie>
	<cookie id="__utmt">
		<host>.corrieredellumbria.corr.it</host>
		<isdomain>TRUE</isdomain>
		<path>/</path>
		<issecure>FALSE</issecure>
		<expires>1478263530</expires>
		<name>__utmt</name>
		<value><![CDATA[1]]></value>
		<policy>0</policy>
		<status>0</status>
	</cookie>
	<cookie id="JSESSIONID">
		<host>corrieredellumbria.corr.it</host>
		<isdomain>FALSE</isdomain>
		<path>/</path>
		<issecure>FALSE</issecure>
		<expires>0</expires>
		<name>JSESSIONID</name>
		<value><![CDATA[8FEC267BAE9F438AAF78F643BCDA93C1]]></value>
		<policy>0</policy>
		<status>0</status>
	</cookie>
	<cookie id="JSESSIONID">
		<host>corrierediarezzo.corr.it</host>
		<isdomain>FALSE</isdomain>
		<path>/</path>
		<issecure>FALSE</issecure>
		<expires>0</expires>
		<name>JSESSIONID</name>
		<value><![CDATA[8FEC267BAE9F438AAF78F643BCDA93C1]]></value>
		<policy>0</policy>
		<status>0</status>
	</cookie>
	<cookie id="JSESSIONID">
		<host>corrieredisiena.corr.it</host>
		<isdomain>FALSE</isdomain>
		<path>/</path>
		<issecure>FALSE</issecure>
		<expires>0</expires>
		<name>JSESSIONID</name>
		<value><![CDATA[8FEC267BAE9F438AAF78F643BCDA93C1]]></value>
		<policy>0</policy>
		<status>0</status>
	</cookie>
	<cookie id="JSESSIONID">
		<host>www.corr.it</host>
		<isdomain>FALSE</isdomain>
		<path>/</path>
		<issecure>FALSE</issecure>
		<expires>0</expires>
		<name>JSESSIONID</name>
		<value><![CDATA[8FEC267BAE9F438AAF78F643BCDA93C1]]></value>
		<policy>0</policy>
		<status>0</status>
	</cookie>
	<cookie id="JSESSIONID">
		<host>corrierediviterbo.corr.it</host>
		<isdomain>FALSE</isdomain>
		<path>/</path>
		<issecure>FALSE</issecure>
		<expires>0</expires>
		<name>JSESSIONID</name>
		<value><![CDATA[8FEC267BAE9F438AAF78F643BCDA93C1]]></value>
		<policy>0</policy>
		<status>0</status>
	</cookie>
	<cookie id="JSESSIONID">
		<host>corrieredirieti.corr.it</host>
		<isdomain>FALSE</isdomain>
		<path>/</path>
		<issecure>FALSE</issecure>
		<expires>0</expires>
		<name>JSESSIONID</name>
		<value><![CDATA[8FEC267BAE9F438AAF78F643BCDA93C1]]></value>
		<policy>0</policy>
		<status>0</status>
	</cookie>
	<cookie id="__gads">
		<host>.corr.it</host>
		<isdomain>TRUE</isdomain>
		<path>/</path>
		<issecure>FALSE</issecure>
		<expires>1541334928</expires>
		<name>__gads</name>
		<value><![CDATA[ID=9cf6edd203fbe226:T=1478262928:S=ALNI_Mb7asEjCjb1YaoigQAxjlRHXzruoQ]]></value>
		<policy>0</policy>
		<status>0</status>
	</cookie>
	<cookie id="JSESSIONID">
		<host>corrieredimaremma.corr.it</host>
		<isdomain>FALSE</isdomain>
		<path>/</path>
		<issecure>FALSE</issecure>
		<expires>0</expires>
		<name>JSESSIONID</name>
		<value><![CDATA[8FEC267BAE9F438AAF78F643BCDA93C1]]></value>
		<policy>0</policy>
		<status>0</status>
	</cookie>
	<cookie id="cc_cookie_decline">
		<host>corrieredellumbria.corr.it</host>
		<isdomain>FALSE</isdomain>
		<path>/</path>
		<issecure>FALSE</issecure>
		<expires>0</expires>
		<name>cc_cookie_decline</name>
		<value><![CDATA[null]]></value>
		<policy>0</policy>
		<status>0</status>
	</cookie>
	<cookie id="virtualcms_cookie_law_settings">
		<host>corrieredellumbria.corr.it</host>
		<isdomain>FALSE</isdomain>
		<path>/</path>
		<issecure>FALSE</issecure>
		<expires>1509798934</expires>
		<name>virtualcms_cookie_law_settings</name>
		<value><![CDATA[%5B%7B%22tag%22%3A%22tecnici%22%2C%22accepted%22%3Atrue%2C%22provider_tag%22%3A%22tecnici%22%7D%2C%7B%22tag%22%3A%22google-analytics-cookies%22%2C%22accepted%22%3Atrue%2C%22provider_tag%22%3A%22google-analytics%22%7D%2C%7B%22tag%22%3A%22facebook%22%2C%22accepted%22%3Atrue%2C%22provider_tag%22%3A%22facebook%22%7D%2C%7B%22tag%22%3A%22addthis%22%2C%22accepted%22%3Atrue%2C%22provider_tag%22%3A%22addthis%22%7D%2C%7B%22tag%22%3A%22twitter%22%2C%22accepted%22%3Atrue%2C%22provider_tag%22%3A%22twitter%22%7D%2C%7B%22tag%22%3A%22webtrekk%22%2C%22accepted%22%3Atrue%2C%22provider_tag%22%3A%22webtrekk%22%7D%2C%7B%22tag%22%3A%22google-adsense%22%2C%22accepted%22%3Atrue%2C%22provider_tag%22%3A%22google-analytics%22%7D%2C%7B%22tag%22%3A%22google-plus%22%2C%22accepted%22%3Atrue%2C%22provider_tag%22%3A%22google-analytics%22%7D%2C%7B%22tag%22%3A%22youtube%22%2C%22accepted%22%3Atrue%2C%22provider_tag%22%3A%22google-analytics%22%7D%2C%7B%22tag%22%3A%22sharethis%22%2C%22accepted%22%3Atrue%2C%22provider_tag%22%3A%22sharethis%22%7D%2C%7B%22tag%22%3A%22manzoni-cookie%22%2C%22accepted%22%3Atrue%2C%22provider_tag%22%3A%22manzoni%22%7D%2C%7B%22tag%22%3A%22videosyndication-elemedia%22%2C%22accepted%22%3Atrue%2C%22provider_tag%22%3A%22videosyndication-elemedia%22%7D%5D]]></value>
		<policy>0</policy>
		<status>0</status>
	</cookie>
	<cookie id="cc_cookie_accept">
		<host>corrieredellumbria.corr.it</host>
		<isdomain>FALSE</isdomain>
		<path>/</path>
		<issecure>FALSE</issecure>
		<expires>1509798934</expires>
		<name>cc_cookie_accept</name>
		<value><![CDATA[cc_cookie_accept]]></value>
		<policy>0</policy>
		<status>0</status>
	</cookie>
	<cookie id="__utma">
		<host>.corrieredellumbria.corr.it</host>
		<isdomain>TRUE</isdomain>
		<path>/</path>
		<issecure>FALSE</issecure>
		<expires>1541334934</expires>
		<name>__utma</name>
		<value><![CDATA[128286110.418023172.1478262930.1478262930.1478262930.1]]></value>
		<policy>0</policy>
		<status>0</status>
	</cookie>
	<cookie id="__utmz">
		<host>.corrieredellumbria.corr.it</host>
		<isdomain>TRUE</isdomain>
		<path>/</path>
		<issecure>FALSE</issecure>
		<expires>1494030934</expires>
		<name>__utmz</name>
		<value><![CDATA[128286110.1478262930.1.1.utmcsr=(direct)|utmccn=(direct)|utmcmd=(none)]]></value>
		<policy>0</policy>
		<status>0</status>
	</cookie>
	<cookie id="__utmb">
		<host>.corrieredellumbria.corr.it</host>
		<isdomain>TRUE</isdomain>
		<path>/</path>
		<issecure>FALSE</issecure>
		<expires>1478264734</expires>
		<name>__utmb</name>
		<value><![CDATA[128286110.2.10.1478262930]]></value>
		<policy>0</policy>
		<status>0</status>
	</cookie>
	<cookie id="__atuvc">
		<host>corrieredellumbria.corr.it</host>
		<isdomain>FALSE</isdomain>
		<path>/</path>
		<issecure>FALSE</issecure>
		<expires>1541334939</expires>
		<name>__atuvc</name>
		<value><![CDATA[1%7C44]]></value>
		<policy>0</policy>
		<status>0</status>
	</cookie>
	<cookie id="__atuvs">
		<host>corrieredellumbria.corr.it</host>
		<isdomain>FALSE</isdomain>
		<path>/</path>
		<issecure>FALSE</issecure>
		<expires>1478264739</expires>
		<name>__atuvs</name>
		<value><![CDATA[581c809ac203010a000]]></value>
		<policy>0</policy>
		<status>0</status>
	</cookie>
	<cookie id="JSESSIONID">
		<host>edicola.corrieredellumbria.it</host>
		<isdomain>FALSE</isdomain>
		<path>/corriere/</path>
		<issecure>FALSE</issecure>
		<expires>0</expires>
		<name>JSESSIONID</name>
		<value><![CDATA[2A196DE9BB0F40932B2100717ACC3441]]></value>
		<policy>0</policy>
		<status>0</status>
	</cookie>
	<cookie id="id">
		<host>.doubleclick.net</host>
		<isdomain>TRUE</isdomain>
		<path>/</path>
		<issecure>FALSE</issecure>
		<expires>1541334934</expires>
		<name>id</name>
		<value><![CDATA[22af7ed70b0e002e||t=1478262932|et=730|cs=002213fd4839521b3748f03d73]]></value>
		<policy>0</policy>
		<status>0</status>
	</cookie>
	<cookie id="IDE">
		<host>.doubleclick.net</host>
		<isdomain>TRUE</isdomain>
		<path>/</path>
		<issecure>FALSE</issecure>
		<expires>1541334934</expires>
		<name>IDE</name>
		<value><![CDATA[AHWqTUlYNXVzXh_cVEmBC29YrelaKwp03Cy94nq7SubKCrDWnCNnMFFclA]]></value>
		<policy>0</policy>
		<status>0</status>
	</cookie>
	<cookie id="DSID">
		<host>.doubleclick.net</host>
		<isdomain>TRUE</isdomain>
		<path>/</path>
		<issecure>FALSE</issecure>
		<expires>1478266541</expires>
		<name>DSID</name>
		<value><![CDATA[NO_DATA]]></value>
		<policy>0</policy>
		<status>0</status>
	</cookie>
	<cookie id="C5">
		<host>.serving-sys.com</host>
		<isdomain>TRUE</isdomain>
		<path>/</path>
		<issecure>FALSE</issecure>
		<expires>1486024541</expires>
		<name>C5</name>
		<value><![CDATA[]]></value>
		<policy>0</policy>
		<status>0</status>
	</cookie>
	<cookie id="D2">
		<host>.serving-sys.com</host>
		<isdomain>TRUE</isdomain>
		<path>/</path>
		<issecure>FALSE</issecure>
		<expires>1486024541</expires>
		<name>D2</name>
		<value><![CDATA[]]></value>
		<policy>0</policy>
		<status>0</status>
	</cookie>
	<cookie id="A6">
		<host>.serving-sys.com</host>
		<isdomain>TRUE</isdomain>
		<path>/</path>
		<issecure>FALSE</issecure>
		<expires>1486024543</expires>
		<name>A6</name>
		<value><![CDATA[02nOIblMk3000d9R000010000]]></value>
		<policy>0</policy>
		<status>0</status>
	</cookie>
	<cookie id="u2">
		<host>.serving-sys.com</host>
		<isdomain>TRUE</isdomain>
		<path>/</path>
		<issecure>FALSE</issecure>
		<expires>1486024543</expires>
		<name>u2</name>
		<value><![CDATA[ba9bcaa7-bca9-4bce-8941-5082ba2e92e54bl00g]]></value>
		<policy>0</policy>
		<status>0</status>
	</cookie>
	<cookie id="eyeblaster">
		<host>.bs.serving-sys.com</host>
		<isdomain>TRUE</isdomain>
		<path>/</path>
		<issecure>FALSE</issecure>
		<expires>1486024543</expires>
		<name>eyeblaster</name>
		<value><![CDATA[FLV=0&RES=128]]></value>
		<policy>0</policy>
		<status>0</status>
	</cookie>
	<cookie id="UID">
		<host>.scorecardresearch.com</host>
		<isdomain>TRUE</isdomain>
		<path>/</path>
		<issecure>FALSE</issecure>
		<expires>1540470939</expires>
		<name>UID</name>
		<value><![CDATA[15495a10111476a1076cedg1478262937]]></value>
		<policy>0</policy>
		<status>0</status>
	</cookie>
	<cookie id="UIDR">
		<host>.scorecardresearch.com</host>
		<isdomain>TRUE</isdomain>
		<path>/</path>
		<issecure>FALSE</issecure>
		<expires>1540470939</expires>
		<name>UIDR</name>
		<value><![CDATA[1478262937]]></value>
		<policy>0</policy>
		<status>0</status>
	</cookie>
</cookies>
